django_annotate/__init__.py
django_annotate/apps.py
django_annotate/config.py
django_annotate/db_introspect/__init__.py
django_annotate/db_introspect/base.py
django_annotate/db_introspect/factory.py
django_annotate/db_introspect/postgresql.py
django_annotate/db_introspect.py
django_annotate/management/__init__.py
django_annotate/management/commands/__init__.py
django_annotate/management/commands/annotate_models.py
django_annotate/parser.py
django_annotate/signals.py
django_annotate-0.3.2.dist-info/LICENSE
django_annotate-0.3.2.dist-info/METADATA
django_annotate-0.3.2.dist-info/WHEEL
django_annotate-0.3.2.dist-info/RECORD
