Metadata-Version: 2.3
Name: django-annotate
Version: 0.3.2
Summary: 
License: MIT
Author: Chris Davis
Requires-Python: >=3.10
Classifier: License :: OSI Approved :: MIT License
Classifier: Programming Language :: Python :: 3
Classifier: Programming Language :: Python :: 3.10
Classifier: Programming Language :: Python :: 3.11
Classifier: Programming Language :: Python :: 3.12
Classifier: Programming Language :: Python :: 3.13
Requires-Dist: django (>=5.2,<6.0)
Requires-Dist: pyyaml (>=6.0,<7.0)
